django_rest_framework_kong_consumers/__init__.py
django_rest_framework_kong_consumers/admin.py
django_rest_framework_kong_consumers/apps.py
django_rest_framework_kong_consumers/authentication.py
django_rest_framework_kong_consumers/functions.py
django_rest_framework_kong_consumers/models.py
django_rest_framework_kong_consumers/runtests.py
django_rest_framework_kong_consumers/serializers.py
django_rest_framework_kong_consumers/settings.py
django_rest_framework_kong_consumers/urls.py
django_rest_framework_kong_consumers/views.py
django_rest_framework_kong_consumers/migrations/0001_initial.py
django_rest_framework_kong_consumers/migrations/__init__.py
django_rest_framework_kong_consumers/tests/__init__.py
django_rest_framework_kong_consumers/tests/test_settings.py
django_rest_framework_kong_consumers/tests/test_views.py
django_rest_framework_kong_consumers-0.1.3.dist-info/AUTHORS.rst
django_rest_framework_kong_consumers-0.1.3.dist-info/LICENSE.txt
django_rest_framework_kong_consumers-0.1.3.dist-info/METADATA
django_rest_framework_kong_consumers-0.1.3.dist-info/WHEEL
django_rest_framework_kong_consumers-0.1.3.dist-info/top_level.txt
django_rest_framework_kong_consumers-0.1.3.dist-info/RECORD
